{
  "generatedAt": "2026-03-12T09:16:48.447Z",
  "provider": "z.ai",
  "model": "glm-5",
  "source": "ai",
  "suggestion": {
    "status": "CHỜ",
    "confidence": "Trung bình",
    "horizon": "1-4 tuần",
    "thesis": "Giá vàng SJC đang ở vùng đỉnh lịch sử 5 năm (percentile 99%) với đà tăng mạnh +2.94%/30 ngày, nhưng thanh khoản có thể giảm và rủi ro điều chỉnh tăng cao khi các yếu tố vĩ mô (lạm phát, USD) đang gây áp lực lên giá vàng thế giới.",
    "reasons": [
      "Giá SJC 186.3 triệu đồng/lượng đang ở phân vị 99% trong 5 năm qua, cho thấy giá đang ở vùng cực kỳ cao so với lịch sử.",
      "Đà tăng giá còn mạnh với change30dPct đạt +2.94%, giá hiện tại cao hơn MA30 (161.38 triệu đồng/lượng) tới 15.4%.",
      "Premium 14.24% nằm trong biên dao động bình thường của 30 ngày qua (11.23% - 17.71%), không có dấu hiệu bong bóng cực đoan.",
      "Giá thế giới XAUUSD giảm nhẹ -0.11%/ngày trong bối cảnh lo ngại lạm phát và USD mạnh lên theo tin tức."
    ],
    "risks": [
      "Rủi ro điều chỉnh giá cao do giá đang ở vùng đỉnh 5 năm (percentile 99%), biên độ dao động 1.4%/ngày có thể gây sốc tài khoản.",
      "Áp lực lạm phát và USD mạnh (theo tin tức) có thể làm giảm giá vàng thế giới, kéo theo giá vàng trong nước.",
      "Dữ liệu vĩ mô first-principles bị thiếu (healthy: false) khiến việc đánh giá xu hướng dài hạn không đầy đủ."
    ],
    "evidence": [
      {
        "key": "SJC Price",
        "value": 186300000,
        "unit": "VND/lượng",
        "source": "market_snapshot"
      },
      {
        "key": "5Y Percentile",
        "value": 99,
        "unit": "%",
        "source": "market_snapshot"
      },
      {
        "key": "Premium vs World",
        "value": 14.24,
        "unit": "%",
        "source": "market_snapshot"
      },
      {
        "key": "Change 30 Days",
        "value": 2.94,
        "unit": "%",
        "source": "market_snapshot"
      },
      {
        "key": "MA30 VND",
        "value": 161375068,
        "unit": "VND/lượng",
        "source": "market_snapshot"
      },
      {
        "key": "XAUUSD Change 1D",
        "value": -0.11,
        "unit": "%",
        "source": "first_principles_context"
      },
      {
        "key": "XAUUSD Change 20D",
        "value": 5.16,
        "unit": "%",
        "source": "first_principles_context"
      },
      {
        "key": "30D Premium Range High",
        "value": 17.71,
        "unit": "%",
        "source": "monthly_series_30d"
      }
    ]
  },
  "marketSnapshot": {
    "latestTimestamp": "2026-03-12T09:15:46.609Z",
    "sjcVndPerTael": 186300000,
    "intlVndPerTael": 163070814.81927255,
    "premiumPct": 14.24,
    "change7dPct": 2.19,
    "change30dPct": 2.94,
    "volatilityDailyPct": 1.4,
    "ma7VndPerTael": 162926700,
    "ma30VndPerTael": 161375068,
    "percentile5y": 99,
    "drawdowns": {
      "total": 4,
      "recovered": 4,
      "notRecovered": 0,
      "worstPct": 41.26,
      "avgRecoveryDays": 1035
    }
  },
  "macroContext": {
    "fetchedAt": "2026-03-12T09:16:07.692Z",
    "healthy": false,
    "missingFactors": [
      "US Dollar Trade Weighted Index",
      "US Real Yield 10Y",
      "US Breakeven Inflation 10Y",
      "US Effective Fed Funds Rate",
      "US Treasury Yield 10Y",
      "US Treasury Yield 2Y",
      "VIX Volatility Index"
    ],
    "factors": [
      {
        "id": "gold_spot_xauusd",
        "name": "Gold Spot XAUUSD",
        "value": 5176.12,
        "unit": "USD/oz",
        "date": "2026-03-12",
        "change1dPct": -0.11,
        "change5dPct": 1.87,
        "change20dPct": 5.16,
        "relationToGold": "context"
      },
      {
        "id": "usd_index_trade_weighted",
        "name": "US Dollar Trade Weighted Index",
        "value": null,
        "unit": "index",
        "date": null,
        "change1dPct": null,
        "change5dPct": null,
        "change20dPct": null,
        "relationToGold": "inverse"
      },
      {
        "id": "us_real_yield_10y",
        "name": "US Real Yield 10Y",
        "value": null,
        "unit": "%",
        "date": null,
        "change1dPct": null,
        "change5dPct": null,
        "change20dPct": null,
        "relationToGold": "inverse"
      },
      {
        "id": "us_breakeven_10y",
        "name": "US Breakeven Inflation 10Y",
        "value": null,
        "unit": "%",
        "date": null,
        "change1dPct": null,
        "change5dPct": null,
        "change20dPct": null,
        "relationToGold": "direct"
      },
      {
        "id": "us_fed_funds_effective",
        "name": "US Effective Fed Funds Rate",
        "value": null,
        "unit": "%",
        "date": null,
        "change1dPct": null,
        "change5dPct": null,
        "change20dPct": null,
        "relationToGold": "inverse"
      },
      {
        "id": "us_treasury_10y",
        "name": "US Treasury Yield 10Y",
        "value": null,
        "unit": "%",
        "date": null,
        "change1dPct": null,
        "change5dPct": null,
        "change20dPct": null,
        "relationToGold": "inverse"
      },
      {
        "id": "us_treasury_2y",
        "name": "US Treasury Yield 2Y",
        "value": null,
        "unit": "%",
        "date": null,
        "change1dPct": null,
        "change5dPct": null,
        "change20dPct": null,
        "relationToGold": "inverse"
      },
      {
        "id": "vix",
        "name": "VIX Volatility Index",
        "value": null,
        "unit": "index",
        "date": null,
        "change1dPct": null,
        "change5dPct": null,
        "change20dPct": null,
        "relationToGold": "direct"
      }
    ],
    "policyHeadlines": [
      "2026-03-11 | ECB Press / Speeches | ECB welcomes decision on new site for European School Frankfurt",
      "2026-03-11 | ECB Press / Speeches | Eurosystem Unveils Appia Roadmap for Europe’s Tokenised Finance",
      "2026-03-09 | ECB Press / Speeches | Frank Elderson: Nature in decline, economy on the line: the importance of international cooperation for managing nature-related risks",
      "2026-03-08 | ECB Press / Speeches | Christine Lagarde: Interview with ELLE Magazine",
      "2026-03-06 | ECB Press / Speeches | Isabel Schnabel: Navigating inflation and employment in an era of supply shocks and AI",
      "2026-03-06 | ECB Press / Speeches | Piero Cipollone: Digital euro"
    ],
    "geopoliticalHeadlines": [
      "2026-03-12 | edenmagnet.com.au | Big four banks predict three consecutive RBA rate hikes",
      "2026-03-12 | moreechampion.com.au | Big four banks predict three consecutive RBA rate hikes",
      "2026-03-12 | braidwoodtimes.com.au | Big four banks predict three consecutive RBA rate hikes"
    ],
    "countryActionHeadlines": [
      "2026-03-12 | actionforex.com | We Believe ECB Will Hike at Next Week Meeting or in April",
      "2026-03-12 | marketscreener.com | Futures point lower as inflation fears resurface",
      "2026-03-12 | batonrougepost.com | Forget the island : Jeffrey Epsteins secret war for Libyas billions",
      "2026-03-12 | economictimes.indiatimes.com | S & P / ASX 200 closes lower as Australian shares slip , oil price surge triggers inflation fears ; check top gainers and losers",
      "2026-03-12 | thoibaotaichinhvietnam.vn | Deposit rate hikes expected to continue as banks compete for liquidity",
      "2026-03-12 | mexicostar.com | Forget the island : Jeffrey Epsteins secret war for Libyas billions"
    ],
    "dollarYieldHeadlines": [
      "2026-03-12 | retail.economictimes.indiatimes.com | Gold Prices Drop as Dollar Strengthens and Inflation Fears Rise , ETRetail",
      "2026-03-12 | marketscreener.com | Futures point lower as inflation fears resurface",
      "2026-03-12 | news18.com | Gold , Silver Prices Fall Today : Check 22K And 24K Rates In Delhi , Mumbai , Other Cities On March 12",
      "2026-03-12 | economictimes.indiatimes.com | S & P / ASX 200 closes lower as Australian shares slip , oil price surge triggers inflation fears ; check top gainers and losers"
    ]
  }
}