{
  "fetchedAt": "2026-07-02T20:16:57.634Z",
  "days": 30,
  "exchangeRate": {
    "usdVnd": 26251.15,
    "fetchedAt": "2026-07-02T20:16:57.629Z"
  },
  "data": [
    {
      "date": "2026-06-02",
      "usdPerOunce": 4488.67153,
      "usdPerGram": 144.31403314739498,
      "vndPerGram": 3788409.331257238,
      "vndPerTael": 142065349.92214644
    },
    {
      "date": "2026-06-03",
      "usdPerOunce": 4434.46857,
      "usdPerGram": 142.57136881701416,
      "vndPerGram": 3742662.3885207614,
      "vndPerTael": 140349839.56952855
    },
    {
      "date": "2026-06-04",
      "usdPerOunce": 4475.96582,
      "usdPerGram": 143.9055353899079,
      "vndPerGram": 3777685.7953507807,
      "vndPerTael": 141663217.32565427
    },
    {
      "date": "2026-06-05",
      "usdPerOunce": 4328.95948,
      "usdPerGram": 139.17917533396565,
      "vndPerGram": 3653613.4085682323,
      "vndPerTael": 137010502.8213087
    },
    {
      "date": "2026-06-06",
      "usdPerOunce": 4330.15149,
      "usdPerGram": 139.21749931679716,
      "vndPerGram": 3654619.45719014,
      "vndPerTael": 137048229.64463025
    },
    {
      "date": "2026-06-07",
      "usdPerOunce": 4330.1492,
      "usdPerGram": 139.2174256916424,
      "vndPerGram": 3654617.524445159,
      "vndPerTael": 137048157.16669345
    },
    {
      "date": "2026-06-08",
      "usdPerOunce": 4330.19194,
      "usdPerGram": 139.2187998135258,
      "vndPerGram": 3654653.596724838,
      "vndPerTael": 137049509.8771814
    },
    {
      "date": "2026-06-09",
      "usdPerOunce": 4260.08482,
      "usdPerGram": 136.9648052469979,
      "vndPerGram": 3595483.6472597294,
      "vndPerTael": 134830636.77223986
    },
    {
      "date": "2026-06-10",
      "usdPerOunce": 4071.58097,
      "usdPerGram": 130.90427025897407,
      "vndPerGram": 3436387.6342088673,
      "vndPerTael": 128864536.28283252
    },
    {
      "date": "2026-06-11",
      "usdPerOunce": 4211.07514,
      "usdPerGram": 135.38910862121625,
      "vndPerGram": 3554119.798781841,
      "vndPerTael": 133279492.45431904
    },
    {
      "date": "2026-06-12",
      "usdPerOunce": 4217.96336,
      "usdPerGram": 135.61056987155786,
      "vndPerGram": 3559933.4112837464,
      "vndPerTael": 133497502.9231405
    },
    {
      "date": "2026-06-13",
      "usdPerOunce": 4215.38604,
      "usdPerGram": 135.52770717121868,
      "vndPerGram": 3557758.1701077376,
      "vndPerTael": 133415931.37904017
    },
    {
      "date": "2026-06-14",
      "usdPerOunce": 4215.36946,
      "usdPerGram": 135.52717411223816,
      "vndPerGram": 3557744.1766964807,
      "vndPerTael": 133415406.62611803
    },
    {
      "date": "2026-06-15",
      "usdPerOunce": 4309.42435,
      "usdPerGram": 138.55110678862508,
      "vndPerGram": 3637125.8869742155,
      "vndPerTael": 136392220.76153308
    },
    {
      "date": "2026-06-16",
      "usdPerOunce": 4331.36946,
      "usdPerGram": 139.25665793238701,
      "vndPerGram": 3655647.4158817814,
      "vndPerTael": 137086778.0955668
    },
    {
      "date": "2026-06-17",
      "usdPerOunce": 4258.07298,
      "usdPerGram": 136.9001231372675,
      "vndPerGram": 3593785.6674948805,
      "vndPerTael": 134766962.531058
    },
    {
      "date": "2026-06-18",
      "usdPerOunce": 4209.12291,
      "usdPerGram": 135.3263430160593,
      "vndPerGram": 3552472.129466025,
      "vndPerTael": 133217704.85497594
    },
    {
      "date": "2026-06-19",
      "usdPerOunce": 4156.6112,
      "usdPerGram": 133.63805359525455,
      "vndPerGram": 3508152.5906370664,
      "vndPerTael": 131555722.14888999
    },
    {
      "date": "2026-06-20",
      "usdPerOunce": 4156.51085,
      "usdPerGram": 133.63482727024288,
      "vndPerGram": 3508067.8958952366,
      "vndPerTael": 131552546.09607138
    },
    {
      "date": "2026-06-21",
      "usdPerOunce": 4156.5162,
      "usdPerGram": 133.63499927660874,
      "vndPerGram": 3508072.4112601476,
      "vndPerTael": 131552715.42225553
    },
    {
      "date": "2026-06-22",
      "usdPerOunce": 4191.78368,
      "usdPerGram": 134.7688742424486,
      "vndPerGram": 3537837.9330696543,
      "vndPerTael": 132668922.49011204
    },
    {
      "date": "2026-06-23",
      "usdPerOunce": 4110.44546,
      "usdPerGram": 132.15379169546836,
      "vndPerGram": 3469189.0088664945,
      "vndPerTael": 130094587.83249354
    },
    {
      "date": "2026-06-24",
      "usdPerOunce": 4001.11524,
      "usdPerGram": 128.63874612181908,
      "vndPerGram": 3376915.020255791,
      "vndPerTael": 126634313.25959216
    },
    {
      "date": "2026-06-25",
      "usdPerOunce": 4026.44634,
      "usdPerGram": 129.45315929075505,
      "vndPerGram": 3398294.302515505,
      "vndPerTael": 127436036.34433143
    },
    {
      "date": "2026-06-26",
      "usdPerOunce": 4088.92554,
      "usdPerGram": 131.46191071744337,
      "vndPerGram": 3451026.337530214,
      "vndPerTael": 129413487.65738302
    },
    {
      "date": "2026-06-27",
      "usdPerOunce": 4080.81341,
      "usdPerGram": 131.20109987621973,
      "vndPerGram": 3444179.7530156258,
      "vndPerTael": 129156740.73808597
    },
    {
      "date": "2026-06-28",
      "usdPerOunce": 4080.80878,
      "usdPerGram": 131.20095101837413,
      "vndPerGram": 3444175.845325992,
      "vndPerTael": 129156594.1997247
    },
    {
      "date": "2026-06-29",
      "usdPerOunce": 4016.52691,
      "usdPerGram": 129.13424244859903,
      "vndPerGram": 3389922.3686545403,
      "vndPerTael": 127122088.82454526
    },
    {
      "date": "2026-06-30",
      "usdPerOunce": 4007.70422,
      "usdPerGram": 128.8505865899336,
      "vndPerGram": 3382476.076160336,
      "vndPerTael": 126842852.8560126
    },
    {
      "date": "2026-07-01",
      "usdPerOunce": 4031.56804,
      "usdPerGram": 129.61782564663142,
      "vndPerGram": 3402616.9837235687,
      "vndPerTael": 127598136.88963383
    },
    {
      "date": "2026-07-02",
      "usdPerOunce": 4120.28163,
      "usdPerGram": 132.47003166846176,
      "vndPerGram": 3477490.67183354,
      "vndPerTael": 130405900.19375774
    }
  ]
}