{
  "timestamp": "2026-05-31T22:22:53.342Z",
  "normalized": [
    {
      "source": "TwelveData",
      "country": "International",
      "originalCurrency": "USD",
      "originalPricePerGram": 145.7954175575096,
      "vndPerGram": 3833428.0729231117,
      "vndPerTael": 143753552.7346167
    },
    {
      "source": "SJC Miếng",
      "country": "Vietnam",
      "originalCurrency": "VND",
      "originalPricePerGram": 4240000,
      "vndPerGram": 4240000,
      "vndPerTael": 159000000
    },
    {
      "source": "SJC Nhẫn",
      "country": "Vietnam",
      "originalCurrency": "VND",
      "originalPricePerGram": 4234666.666666667,
      "vndPerGram": 4234666.666666667,
      "vndPerTael": 158800000
    },
    {
      "source": "GoldPricez-VN",
      "country": "Vietnam",
      "originalCurrency": "VND",
      "originalPricePerGram": 3829259.84,
      "vndPerGram": 3829259.84,
      "vndPerTael": 143597244
    },
    {
      "source": "Calculated (XAUUSD × USD/CNY)",
      "country": "China",
      "originalCurrency": "CNY",
      "originalPricePerGram": 989.9508852154903,
      "vndPerGram": 3833428.0729231117,
      "vndPerTael": 143753552.7346167
    },
    {
      "source": "Calculated (XAUUSD × USD/RUB)",
      "country": "Russia",
      "originalCurrency": "RUB",
      "originalPricePerGram": 10360.222371636632,
      "vndPerGram": 3833428.072923111,
      "vndPerTael": 143753552.73461667
    }
  ],
  "raw": {
    "vietnam": [
      {
        "source": "SJC Miếng",
        "country": "Vietnam",
        "currency": "VND",
        "pricePerTael": 159000000,
        "buyPrice": 156000000,
        "sellPrice": 159000000,
        "timestamp": "2026-05-31T22:22:52.568Z",
        "raw": {
          "name": "SJC",
          "buyText": "156.000",
          "sellText": "159.000",
          "type": "Miếng"
        }
      },
      {
        "source": "SJC Nhẫn",
        "country": "Vietnam",
        "currency": "VND",
        "pricePerTael": 158800000,
        "buyPrice": 155800000,
        "sellPrice": 158800000,
        "timestamp": "2026-05-31T22:22:52.572Z",
        "raw": {
          "name": "SJC",
          "buyText": "155.800",
          "sellText": "158.800",
          "type": "Nhẫn"
        }
      },
      {
        "source": "GoldPricez-VN",
        "country": "Vietnam",
        "currency": "VND",
        "pricePerGram": 3829259.84,
        "pricePerTael": 143597244,
        "timestamp": "2026-05-31T22:22:52.052Z",
        "raw": {
          "matched": "\n    \n     = 3,829,259.84  \n    \n        \n    \n        VND \n    \n    \n     ?\n     \n"
        }
      }
    ],
    "international": [
      {
        "source": "TwelveData",
        "country": "International",
        "currency": "USD",
        "pricePerOunce": 4534.74777,
        "pricePerGram": 145.7954175575096,
        "timestamp": "2026-06-01T00:00:00.000Z",
        "raw": {
          "datetime": "2026-06-01",
          "open": "4542.51773",
          "high": "4547.2852",
          "low": "4516.71183",
          "close": "4534.74777"
        }
      }
    ],
    "china": [
      {
        "source": "Calculated (XAUUSD × USD/CNY)",
        "country": "China",
        "currency": "CNY",
        "pricePerOunce": 30790.9373583,
        "pricePerGram": 989.9508852154903,
        "timestamp": "2026-05-31T00:00:00.000Z",
        "raw": {
          "xauusdPrice": 4534.74777,
          "cnyRate": 6.79
        }
      }
    ],
    "russia": [
      {
        "source": "Calculated (XAUUSD × USD/RUB)",
        "country": "Russia",
        "currency": "RUB",
        "pricePerOunce": 322239.1765362,
        "pricePerGram": 10360.222371636632,
        "timestamp": "2026-05-31T00:00:00.000Z",
        "raw": {
          "xauusdPrice": 4534.74777,
          "rubRate": 71.06
        }
      }
    ],
    "india": []
  },
  "exchangeRates": {
    "USD": 1,
    "VND": 26293.2,
    "CNY": 6.79,
    "RUB": 71.06,
    "INR": 95.2
  },
  "vietnamPremium": {
    "premiumPercent": 10.605962061702751,
    "benchmarkVND": 143753552.7346167,
    "localPriceVND": 159000000
  }
}