{
  "timestamp": "2026-01-27T10:16:16.525Z",
  "normalized": [
    {
      "source": "TwelveData",
      "country": "International",
      "originalCurrency": "USD",
      "originalPricePerGram": 163.87087658945134,
      "vndPerGram": 4275576.344309332,
      "vndPerTael": 160334112.91159993
    },
    {
      "source": "SJC Miếng",
      "country": "Vietnam",
      "originalCurrency": "VND",
      "originalPricePerGram": 4728000,
      "vndPerGram": 4728000,
      "vndPerTael": 177300000
    },
    {
      "source": "SJC Nhẫn",
      "country": "Vietnam",
      "originalCurrency": "VND",
      "originalPricePerGram": 4709333.333333333,
      "vndPerGram": 4709333.333333333,
      "vndPerTael": 176600000
    },
    {
      "source": "GoldPricez-VN",
      "country": "Vietnam",
      "originalCurrency": "VND",
      "originalPricePerGram": 4282002.03,
      "vndPerGram": 4282002.03,
      "vndPerTael": 160575076.125
    },
    {
      "source": "GoldPrice.org-CNY",
      "country": "China",
      "originalCurrency": "CNY",
      "originalPricePerGram": 1139.8615718488272,
      "vndPerGram": 4266897.625984518,
      "vndPerTael": 160008660.97441941
    },
    {
      "source": "GoldPrice.org-RUB",
      "country": "Russia",
      "originalCurrency": "RUB",
      "originalPricePerGram": 12527.982760782548,
      "vndPerGram": 4272800.350971717,
      "vndPerTael": 160230013.1614394
    },
    {
      "source": "IBJA-gold 999",
      "country": "India",
      "originalCurrency": "INR",
      "originalPricePerGram": 15902.7,
      "vndPerGram": 4519819.314281046,
      "vndPerTael": 169493224.28553924
    }
  ],
  "raw": {
    "vietnam": [
      {
        "source": "SJC Miếng",
        "country": "Vietnam",
        "currency": "VND",
        "pricePerTael": 177300000,
        "buyPrice": 175300000,
        "sellPrice": 177300000,
        "timestamp": "2026-01-27T10:16:15.475Z",
        "raw": {
          "name": "SJC",
          "buyText": "175.300",
          "sellText": "177.300",
          "type": "Miếng"
        }
      },
      {
        "source": "SJC Nhẫn",
        "country": "Vietnam",
        "currency": "VND",
        "pricePerTael": 176600000,
        "buyPrice": 174100000,
        "sellPrice": 176600000,
        "timestamp": "2026-01-27T10:16:15.476Z",
        "raw": {
          "name": "SJC",
          "buyText": "174.100",
          "sellText": "176.600",
          "type": "Nhẫn"
        }
      },
      {
        "source": "GoldPricez-VN",
        "country": "Vietnam",
        "currency": "VND",
        "pricePerGram": 4282002.03,
        "pricePerTael": 160575076.125,
        "timestamp": "2026-01-27T10:16:16.516Z",
        "raw": {
          "matched": "\n    \n     = 4,282,002.03  \n    \n        \n    \n        VND \n    \n    \n     ?\n     \n"
        }
      }
    ],
    "international": [
      {
        "source": "TwelveData",
        "country": "International",
        "currency": "USD",
        "pricePerOunce": 5096.95781,
        "pricePerGram": 163.87087658945134,
        "timestamp": "2026-01-27T00:00:00.000Z",
        "raw": {
          "datetime": "2026-01-27",
          "open": "5029.23113",
          "high": "5102.59816",
          "low": "4999.05307",
          "close": "5096.95781"
        }
      }
    ],
    "china": [
      {
        "source": "GoldPrice.org-CNY",
        "country": "China",
        "currency": "CNY",
        "pricePerOunce": 35453.6844,
        "pricePerGram": 1139.8615718488272,
        "timestamp": null,
        "raw": {
          "curr": "CNY",
          "xauPrice": 35453.6844,
          "xagPrice": 785.78,
          "chgXau": 94.82,
          "chgXag": -17.4445,
          "pcXau": 0.2682,
          "pcXag": -2.1718,
          "xauClose": 35358.86443,
          "xagClose": 803.22451
        }
      }
    ],
    "russia": [
      {
        "source": "GoldPrice.org-RUB",
        "country": "Russia",
        "currency": "RUB",
        "pricePerOunce": 389664.1118,
        "pricePerGram": 12527.982760782548,
        "timestamp": null,
        "raw": {
          "curr": "RUB",
          "xauPrice": 389664.1118,
          "xagPrice": 8637.2614,
          "chgXau": 630.6153,
          "chgXag": -200.9465,
          "pcXau": 0.1621,
          "pcXag": -2.2736,
          "xauClose": 389033.49655,
          "xagClose": 8838.20788
        }
      }
    ],
    "india": [
      {
        "source": "IBJA-gold 999",
        "country": "India",
        "currency": "INR",
        "pricePerGram": 15902.7,
        "timestamp": "2026-01-27T10:16:15.953Z",
        "raw": {
          "label": "gold 999",
          "priceText": "159027",
          "note": "Original price per 10g"
        }
      }
    ]
  },
  "exchangeRates": {
    "USD": 1,
    "VND": 26091.13,
    "CNY": 6.97,
    "RUB": 76.5,
    "INR": 91.8
  },
  "vietnamPremium": {
    "premiumPercent": 10.58158290853188,
    "benchmarkVND": 160334112.91159993,
    "localPriceVND": 177300000
  }
}