{
  "timestamp": "2026-07-06T02:52:39.271Z",
  "normalized": [
    {
      "source": "TwelveData",
      "country": "International",
      "originalCurrency": "USD",
      "originalPricePerGram": 134.21025993859212,
      "vndPerGram": 3516959.7301518153,
      "vndPerTael": 131885989.88069308
    },
    {
      "source": "SJC Miếng",
      "country": "Vietnam",
      "originalCurrency": "VND",
      "originalPricePerGram": 4037333.3333333335,
      "vndPerGram": 4037333.3333333335,
      "vndPerTael": 151400000
    },
    {
      "source": "SJC Nhẫn",
      "country": "Vietnam",
      "originalCurrency": "VND",
      "originalPricePerGram": 4034666.6666666665,
      "vndPerGram": 4034666.6666666665,
      "vndPerTael": 151300000
    },
    {
      "source": "GoldPricez-VN",
      "country": "Vietnam",
      "originalCurrency": "VND",
      "originalPricePerGram": 3529875.66,
      "vndPerGram": 3529875.66,
      "vndPerTael": 132370337.25
    },
    {
      "source": "Calculated (XAUUSD × USD/CNY)",
      "country": "China",
      "originalCurrency": "CNY",
      "originalPricePerGram": 911.2876649830404,
      "vndPerGram": 3516959.730151815,
      "vndPerTael": 131885989.88069306
    },
    {
      "source": "Calculated (XAUUSD × USD/RUB)",
      "country": "Russia",
      "originalCurrency": "RUB",
      "originalPricePerGram": 10375.795195852557,
      "vndPerGram": 3516959.7301518153,
      "vndPerTael": 131885989.88069308
    }
  ],
  "raw": {
    "vietnam": [
      {
        "source": "SJC Miếng",
        "country": "Vietnam",
        "currency": "VND",
        "pricePerTael": 151400000,
        "buyPrice": 148400000,
        "sellPrice": 151400000,
        "timestamp": "2026-07-06T02:52:38.760Z",
        "raw": {
          "name": "SJC",
          "buyText": "148.400",
          "sellText": "151.400",
          "type": "Miếng"
        }
      },
      {
        "source": "SJC Nhẫn",
        "country": "Vietnam",
        "currency": "VND",
        "pricePerTael": 151300000,
        "buyPrice": 148300000,
        "sellPrice": 151300000,
        "timestamp": "2026-07-06T02:52:38.763Z",
        "raw": {
          "name": "SJC",
          "buyText": "148.300",
          "sellText": "151.300",
          "type": "Nhẫn"
        }
      },
      {
        "source": "GoldPricez-VN",
        "country": "Vietnam",
        "currency": "VND",
        "pricePerGram": 3529875.66,
        "pricePerTael": 132370337.25,
        "timestamp": "2026-07-06T02:52:38.203Z",
        "raw": {
          "matched": "\n    \n     = 3,529,875.66  \n    \n        \n    \n        VND \n    \n    \n     ?\n     \n"
        }
      }
    ],
    "international": [
      {
        "source": "TwelveData",
        "country": "International",
        "currency": "USD",
        "pricePerOunce": 4174.40882,
        "pricePerGram": 134.21025993859212,
        "timestamp": "2026-07-06T00:00:00.000Z",
        "raw": {
          "datetime": "2026-07-06",
          "open": "4174.96346",
          "high": "4202.03378",
          "low": "4169.27246",
          "close": "4174.40882"
        }
      }
    ],
    "china": [
      {
        "source": "Calculated (XAUUSD × USD/CNY)",
        "country": "China",
        "currency": "CNY",
        "pricePerOunce": 28344.235887799998,
        "pricePerGram": 911.2876649830404,
        "timestamp": "2026-07-06T00:00:00.000Z",
        "raw": {
          "xauusdPrice": 4174.40882,
          "cnyRate": 6.79
        }
      }
    ],
    "russia": [
      {
        "source": "Calculated (XAUUSD × USD/RUB)",
        "country": "Russia",
        "currency": "RUB",
        "pricePerOunce": 322723.5458742,
        "pricePerGram": 10375.795195852557,
        "timestamp": "2026-07-06T00:00:00.000Z",
        "raw": {
          "xauusdPrice": 4174.40882,
          "rubRate": 77.31
        }
      }
    ],
    "india": []
  },
  "exchangeRates": {
    "USD": 1,
    "VND": 26204.85,
    "CNY": 6.79,
    "RUB": 77.31,
    "INR": 95.34
  },
  "vietnamPremium": {
    "premiumPercent": 14.796120601558755,
    "benchmarkVND": 131885989.88069308,
    "localPriceVND": 151400000
  }
}