{
  "timestamp": "2026-03-19T18:17:34.738Z",
  "normalized": [
    {
      "source": "TwelveData",
      "country": "International",
      "originalCurrency": "USD",
      "originalPricePerGram": 148.40296268908645,
      "vndPerGram": 3887759.902514058,
      "vndPerTael": 145790996.34427717
    },
    {
      "source": "SJC Miếng",
      "country": "Vietnam",
      "originalCurrency": "VND",
      "originalPricePerGram": 4680000,
      "vndPerGram": 4680000,
      "vndPerTael": 175500000
    },
    {
      "source": "SJC Nhẫn",
      "country": "Vietnam",
      "originalCurrency": "VND",
      "originalPricePerGram": 4672000,
      "vndPerGram": 4672000,
      "vndPerTael": 175200000
    },
    {
      "source": "GoldPricez-VN",
      "country": "Vietnam",
      "originalCurrency": "VND",
      "originalPricePerGram": 3896540.7,
      "vndPerGram": 3896540.7,
      "vndPerTael": 146120276.25
    },
    {
      "source": "Calculated (XAUUSD × USD/CNY)",
      "country": "China",
      "originalCurrency": "CNY",
      "originalPricePerGram": 1025.4644721815873,
      "vndPerGram": 3887759.902514058,
      "vndPerTael": 145790996.34427717
    },
    {
      "source": "Calculated (XAUUSD × USD/RUB)",
      "country": "Russia",
      "originalCurrency": "RUB",
      "originalPricePerGram": 12410.939769688299,
      "vndPerGram": 3887759.902514058,
      "vndPerTael": 145790996.34427717
    },
    {
      "source": "IBJA-gold 999",
      "country": "India",
      "originalCurrency": "INR",
      "originalPricePerGram": 15163.7,
      "vndPerGram": 4267357.409861425,
      "vndPerTael": 160025902.86980343
    }
  ],
  "raw": {
    "vietnam": [
      {
        "source": "SJC Miếng",
        "country": "Vietnam",
        "currency": "VND",
        "pricePerTael": 175500000,
        "buyPrice": 172500000,
        "sellPrice": 175500000,
        "timestamp": "2026-03-19T18:17:34.025Z",
        "raw": {
          "name": "SJC",
          "buyText": "172.500",
          "sellText": "175.500",
          "type": "Miếng"
        }
      },
      {
        "source": "SJC Nhẫn",
        "country": "Vietnam",
        "currency": "VND",
        "pricePerTael": 175200000,
        "buyPrice": 172200000,
        "sellPrice": 175200000,
        "timestamp": "2026-03-19T18:17:34.029Z",
        "raw": {
          "name": "SJC",
          "buyText": "172.200",
          "sellText": "175.200",
          "type": "Nhẫn"
        }
      },
      {
        "source": "GoldPricez-VN",
        "country": "Vietnam",
        "currency": "VND",
        "pricePerGram": 3896540.7,
        "pricePerTael": 146120276.25,
        "timestamp": "2026-03-19T18:17:33.476Z",
        "raw": {
          "matched": "\n    \n     = 3,896,540.7  \n    \n        \n    \n        VND \n    \n    \n     ?\n     \n"
        }
      }
    ],
    "international": [
      {
        "source": "TwelveData",
        "country": "International",
        "currency": "USD",
        "pricePerOunce": 4615.85155,
        "pricePerGram": 148.40296268908645,
        "timestamp": "2026-03-19T00:00:00.000Z",
        "raw": {
          "datetime": "2026-03-19",
          "open": "4842.10656",
          "high": "4868.11576",
          "low": "4514.89843",
          "close": "4615.85155"
        }
      }
    ],
    "china": [
      {
        "source": "Calculated (XAUUSD × USD/CNY)",
        "country": "China",
        "currency": "CNY",
        "pricePerOunce": 31895.5342105,
        "pricePerGram": 1025.4644721815873,
        "timestamp": "2026-03-19T00:00:00.000Z",
        "raw": {
          "xauusdPrice": 4615.85155,
          "cnyRate": 6.91
        }
      }
    ],
    "russia": [
      {
        "source": "Calculated (XAUUSD × USD/RUB)",
        "country": "Russia",
        "currency": "RUB",
        "pricePerOunce": 386023.6651265,
        "pricePerGram": 12410.939769688299,
        "timestamp": "2026-03-19T00:00:00.000Z",
        "raw": {
          "xauusdPrice": 4615.85155,
          "rubRate": 83.63
        }
      }
    ],
    "india": [
      {
        "source": "IBJA-gold 999",
        "country": "India",
        "currency": "INR",
        "pricePerGram": 15163.7,
        "timestamp": "2026-03-19T18:17:34.723Z",
        "raw": {
          "label": "gold 999",
          "priceText": "151637",
          "note": "Original price per 10g"
        }
      }
    ]
  },
  "exchangeRates": {
    "USD": 1,
    "VND": 26197.32,
    "CNY": 6.91,
    "RUB": 83.63,
    "INR": 93.09
  },
  "vietnamPremium": {
    "premiumPercent": 20.377804117317847,
    "benchmarkVND": 145790996.34427717,
    "localPriceVND": 175500000
  }
}