{
  "timestamp": "2026-02-25T17:23:24.065Z",
  "normalized": [
    {
      "source": "TwelveData",
      "country": "International",
      "originalCurrency": "USD",
      "originalPricePerGram": 167.6233935087691,
      "vndPerGram": 4376271.328112502,
      "vndPerTael": 164110174.8042188
    },
    {
      "source": "SJC Miếng",
      "country": "Vietnam",
      "originalCurrency": "VND",
      "originalPricePerGram": 4941333.333333333,
      "vndPerGram": 4941333.333333333,
      "vndPerTael": 185300000
    },
    {
      "source": "SJC Nhẫn",
      "country": "Vietnam",
      "originalCurrency": "VND",
      "originalPricePerGram": 4928000,
      "vndPerGram": 4928000,
      "vndPerTael": 184800000
    },
    {
      "source": "GoldPricez-VN",
      "country": "Vietnam",
      "originalCurrency": "VND",
      "originalPricePerGram": 4377210.91,
      "vndPerGram": 4377210.91,
      "vndPerTael": 164145409.125
    },
    {
      "source": "GoldPrice.org-CNY",
      "country": "China",
      "originalCurrency": "CNY",
      "originalPricePerGram": 1151.7978105357918,
      "vndPerGram": 4364421.016835112,
      "vndPerTael": 163665788.1313167
    },
    {
      "source": "GoldPrice.org-RUB",
      "country": "Russia",
      "originalCurrency": "RUB",
      "originalPricePerGram": 12953.155268699664,
      "vndPerGram": 4414854.686657263,
      "vndPerTael": 165557050.74964735
    },
    {
      "source": "IBJA-gold 999",
      "country": "India",
      "originalCurrency": "INR",
      "originalPricePerGram": 15982.3,
      "vndPerGram": 4587313.683465259,
      "vndPerTael": 172024263.12994722
    }
  ],
  "raw": {
    "vietnam": [
      {
        "source": "SJC Miếng",
        "country": "Vietnam",
        "currency": "VND",
        "pricePerTael": 185300000,
        "buyPrice": 182300000,
        "sellPrice": 185300000,
        "timestamp": "2026-02-25T17:23:23.392Z",
        "raw": {
          "name": "SJC",
          "buyText": "182.300",
          "sellText": "185.300",
          "type": "Miếng"
        }
      },
      {
        "source": "SJC Nhẫn",
        "country": "Vietnam",
        "currency": "VND",
        "pricePerTael": 184800000,
        "buyPrice": 181800000,
        "sellPrice": 184800000,
        "timestamp": "2026-02-25T17:23:23.396Z",
        "raw": {
          "name": "SJC",
          "buyText": "181.800",
          "sellText": "184.800",
          "type": "Nhẫn"
        }
      },
      {
        "source": "GoldPricez-VN",
        "country": "Vietnam",
        "currency": "VND",
        "pricePerGram": 4377210.91,
        "pricePerTael": 164145409.125,
        "timestamp": "2026-02-25T17:23:22.902Z",
        "raw": {
          "matched": "\n    \n     = 4,377,210.91  \n    \n        \n    \n        VND \n    \n    \n     ?\n     \n"
        }
      }
    ],
    "international": [
      {
        "source": "TwelveData",
        "country": "International",
        "currency": "USD",
        "pricePerOunce": 5213.67422,
        "pricePerGram": 167.6233935087691,
        "timestamp": "2026-02-25T00:00:00.000Z",
        "raw": {
          "datetime": "2026-02-25",
          "open": "5154.62929",
          "high": "5218.1188",
          "low": "5123.07465",
          "close": "5213.67422"
        }
      }
    ],
    "china": [
      {
        "source": "GoldPrice.org-CNY",
        "country": "China",
        "currency": "CNY",
        "pricePerOunce": 35824.9432,
        "pricePerGram": 1151.7978105357918,
        "timestamp": null,
        "raw": {
          "curr": "CNY",
          "xauPrice": 35824.9432,
          "xagPrice": 623.53,
          "chgXau": 312.2998,
          "chgXag": 21.072,
          "pcXau": 0.8794,
          "pcXag": 3.4977,
          "xauClose": 35512.64336,
          "xagClose": 602.45795
        }
      }
    ],
    "russia": [
      {
        "source": "GoldPrice.org-RUB",
        "country": "Russia",
        "currency": "RUB",
        "pricePerOunce": 402888.4649,
        "pricePerGram": 12953.155268699664,
        "timestamp": null,
        "raw": {
          "curr": "RUB",
          "xauPrice": 402888.4649,
          "xagPrice": 7010.1188,
          "chgXau": 8013.5341,
          "chgXag": 311.536,
          "pcXau": 2.0294,
          "pcXag": 4.6508,
          "xauClose": 394874.93076,
          "xagClose": 6698.58277
        }
      }
    ],
    "india": [
      {
        "source": "IBJA-gold 999",
        "country": "India",
        "currency": "INR",
        "pricePerGram": 15982.3,
        "timestamp": "2026-02-25T17:23:24.049Z",
        "raw": {
          "label": "gold 999",
          "priceText": "159823",
          "note": "Original price per 10g"
        }
      }
    ]
  },
  "exchangeRates": {
    "USD": 1,
    "VND": 26107.76,
    "CNY": 6.89,
    "RUB": 76.6,
    "INR": 90.96
  },
  "vietnamPremium": {
    "premiumPercent": 12.91195090192328,
    "benchmarkVND": 164110174.8042188,
    "localPriceVND": 185300000
  }
}