{
  "timestamp": "2026-05-20T12:54:43.109Z",
  "normalized": [
    {
      "source": "TwelveData",
      "country": "International",
      "originalCurrency": "USD",
      "originalPricePerGram": 144.70661629720126,
      "vndPerGram": 3794559.1163902194,
      "vndPerTael": 142295966.86463323
    },
    {
      "source": "SJC Miếng",
      "country": "Vietnam",
      "originalCurrency": "VND",
      "originalPricePerGram": 4320000,
      "vndPerGram": 4320000,
      "vndPerTael": 162000000
    },
    {
      "source": "SJC Nhẫn",
      "country": "Vietnam",
      "originalCurrency": "VND",
      "originalPricePerGram": 4293333.333333333,
      "vndPerGram": 4293333.333333333,
      "vndPerTael": 161000000
    },
    {
      "source": "GoldPricez-VN",
      "country": "Vietnam",
      "originalCurrency": "VND",
      "originalPricePerGram": 3813120.35,
      "vndPerGram": 3813120.35,
      "vndPerTael": 142992013.125
    },
    {
      "source": "Calculated (XAUUSD × USD/CNY)",
      "country": "China",
      "originalCurrency": "CNY",
      "originalPricePerGram": 986.8991231469128,
      "vndPerGram": 3794559.1163902194,
      "vndPerTael": 142295966.86463323
    },
    {
      "source": "Calculated (XAUUSD × USD/RUB)",
      "country": "Russia",
      "originalCurrency": "RUB",
      "originalPricePerGram": 10317.58174199045,
      "vndPerGram": 3794559.1163902194,
      "vndPerTael": 142295966.86463323
    },
    {
      "source": "IBJA-gold 999",
      "country": "India",
      "originalCurrency": "INR",
      "originalPricePerGram": 15796.1,
      "vndPerGram": 4285691.945400931,
      "vndPerTael": 160713447.9525349
    }
  ],
  "raw": {
    "vietnam": [
      {
        "source": "SJC Miếng",
        "country": "Vietnam",
        "currency": "VND",
        "pricePerTael": 162000000,
        "buyPrice": 159000000,
        "sellPrice": 162000000,
        "timestamp": "2026-05-20T12:54:42.927Z",
        "raw": {
          "name": "SJC",
          "buyText": "159.000",
          "sellText": "162.000",
          "type": "Miếng"
        }
      },
      {
        "source": "SJC Nhẫn",
        "country": "Vietnam",
        "currency": "VND",
        "pricePerTael": 161000000,
        "buyPrice": 158000000,
        "sellPrice": 161000000,
        "timestamp": "2026-05-20T12:54:42.929Z",
        "raw": {
          "name": "SJC",
          "buyText": "158.000",
          "sellText": "161.000",
          "type": "Nhẫn"
        }
      },
      {
        "source": "GoldPricez-VN",
        "country": "Vietnam",
        "currency": "VND",
        "pricePerGram": 3813120.35,
        "pricePerTael": 142992013.125,
        "timestamp": "2026-05-20T12:54:42.190Z",
        "raw": {
          "matched": "\n    \n     = 3,813,120.35  \n    \n        \n    \n        VND \n    \n    \n     ?\n     \n"
        }
      }
    ],
    "international": [
      {
        "source": "TwelveData",
        "country": "International",
        "currency": "USD",
        "pricePerOunce": 4500.88224,
        "pricePerGram": 144.70661629720126,
        "timestamp": "2026-05-20T00:00:00.000Z",
        "raw": {
          "datetime": "2026-05-20",
          "open": "4482.10568",
          "high": "4507.34698",
          "low": "4454.14458",
          "close": "4500.88224"
        }
      }
    ],
    "china": [
      {
        "source": "Calculated (XAUUSD × USD/CNY)",
        "country": "China",
        "currency": "CNY",
        "pricePerOunce": 30696.0168768,
        "pricePerGram": 986.8991231469128,
        "timestamp": "2026-05-20T00:00:00.000Z",
        "raw": {
          "xauusdPrice": 4500.88224,
          "cnyRate": 6.82
        }
      }
    ],
    "russia": [
      {
        "source": "Calculated (XAUUSD × USD/RUB)",
        "country": "Russia",
        "currency": "RUB",
        "pricePerOunce": 320912.903712,
        "pricePerGram": 10317.58174199045,
        "timestamp": "2026-05-20T00:00:00.000Z",
        "raw": {
          "xauusdPrice": 4500.88224,
          "rubRate": 71.3
        }
      }
    ],
    "india": [
      {
        "source": "IBJA-gold 999",
        "country": "India",
        "currency": "INR",
        "pricePerGram": 15796.1,
        "timestamp": "2026-05-20T12:54:43.100Z",
        "raw": {
          "label": "gold 999",
          "priceText": "157961",
          "note": "Original price per 10g"
        }
      }
    ]
  },
  "exchangeRates": {
    "USD": 1,
    "VND": 26222.43,
    "CNY": 6.82,
    "RUB": 71.3,
    "INR": 96.65
  },
  "vietnamPremium": {
    "premiumPercent": 13.847218279989129,
    "benchmarkVND": 142295966.86463323,
    "localPriceVND": 162000000
  }
}